[
  {
    "id": "1",
    "first_name": "Urbanus;Esh;uesh0@xrea.com;Male",
    "last_name": "Data Coordinator"
  },
  {
    "id": "2",
    "first_name": "Cornall",
    "last_name": "Laying",
    "email": "claying1@aboutads.info",
    "gender": "Male",
    "job_title": "Pharmacist"
  },
  {
    "id": "3",
    "first_name": "Osbourne",
    "last_name": "Larham",
    "email": "olarham2@newsvine.com",
    "gender": "Male",
    "job_title": "Senior Developer"
  },
  {
    "id": "4",
    "first_name": "Gordie",
    "last_name": "Badwick",
    "email": "gbadwick3@google.fr",
    "gender": "Male",
    "job_title": "Accounting Assistant I"
  },
  {
    "id": "5",
    "first_name": "Sharl",
    "last_name": "Cubbinelli",
    "email": "scubbinelli4@delicious.com",
    "gender": "Female",
    "job_title": "Developer II"
  },
  {
    "id": "6",
    "first_name": "Genevra",
    "last_name": "O'Brian",
    "email": "gobrian5@deviantart.com",
    "gender": "Female",
    "job_title": "Senior Cost Accountant"
  },
  {
    "id": "7",
    "first_name": "Tuckie",
    "last_name": "Hayto",
    "email": "thayto6@cbsnews.com",
    "gender": "Male",
    "job_title": "Analog Circuit Design manager"
  },
  {
    "id": "8",
    "first_name": "Octavia",
    "last_name": "Mumbeson",
    "email": "omumbeson7@fema.gov",
    "gender": "Female",
    "job_title": "Sales Representative"
  },
  {
    "id": "9",
    "first_name": "Ainslie",
    "last_name": "Yakuntsov",
    "email": "ayakuntsov8@blogtalkradio.com",
    "gender": "Female",
    "job_title": "Assistant Manager"
  },
  {
    "id": "10",
    "first_name": "Arline",
    "last_name": "Nitti",
    "email": "anitti9@redcross.org",
    "gender": "Female",
    "job_title": "Civil Engineer"
  }
]